{
  "applications": "*",
  "changelogDate": "20221214180905",
  "dto": "no",
  "embedded": false,
  "entityTableName": "teacher",
  "fields": [
    {
      "fieldName": "firstName",
      "fieldType": "String",
      "fieldValidateRules": ["required"]
    },
    {
      "fieldName": "lastName",
      "fieldType": "String",
      "fieldValidateRules": ["required"]
    },
    {
      "fieldName": "address",
      "fieldType": "String",
      "fieldValidateRules": ["required"]
    },
    {
      "fieldName": "photo",
      "fieldType": "byte[]",
      "fieldTypeBlobContent": "any",
      "fieldValidateRules": ["required"]
    },
    {
      "fieldName": "idProof",
      "fieldType": "byte[]",
      "fieldTypeBlobContent": "any",
      "fieldValidateRules": ["required"]
    },
    {
      "fieldName": "phoneNumber",
      "fieldType": "String",
      "fieldValidateRules": ["required"]
    },
    {
      "fieldName": "emergencyContactNumber",
      "fieldType": "String",
      "fieldValidateRules": ["required"]
    },
    {
      "fieldName": "joiningDate",
      "fieldType": "LocalDate"
    }
  ],
  "fluentMethods": true,
  "jpaMetamodelFiltering": false,
  "name": "Teacher",
  "pagination": "no",
  "readOnly": false,
  "relationships": [],
  "service": "no"
}
